setup.py
PyQtHierarchicalHeaderView/PyQtHierarchicalHeaderView.py
PyQtHierarchicalHeaderView/PyQtProxyModelWithHeaderModels.py
PyQtHierarchicalHeaderView/__init__.py
PyQtHierarchicalHeaderView.egg-info/PKG-INFO
PyQtHierarchicalHeaderView.egg-info/SOURCES.txt
PyQtHierarchicalHeaderView.egg-info/dependency_links.txt
PyQtHierarchicalHeaderView.egg-info/not-zip-safe
PyQtHierarchicalHeaderView.egg-info/top_level.txt