Metadata-Version: 1.0
Name: PyQtHierarchicalHeaderView
Version: 1.0
Summary: Python port of HierarchicalHeaderView
Home-page: https://github.com/robinxb/pyqt-HierarchicalHeaderView
Author: robinxb
Author-email: robinxiaobin@gmail.com
License: MIT
Platform: UNKNOWN
